langchain_pydantic_minifier/__init__.py
langchain_pydantic_minifier/minifier_pydantic.py
langchain_pydantic_minifier-1.0.2.dist-info/LICENSE
langchain_pydantic_minifier-1.0.2.dist-info/METADATA
langchain_pydantic_minifier-1.0.2.dist-info/WHEEL
langchain_pydantic_minifier-1.0.2.dist-info/RECORD
