Metadata-Version: 2.3
Name: langchain-pydantic-minifier
Version: 1.0.2
Summary: automatically reduces token usage by replacing field names with short identifiers (e.g., a, b, c, …), while preserving full descriptions and reversibility.
License: MIT
Author: JulienStitelet
Author-email: julien.stitelet@gmail.com
Requires-Python: >=3.9,<4.0
Classifier: License :: OSI Approved :: MIT License
Classifier: Programming Language :: Python :: 3
Classifier: Programming Language :: Python :: 3.9
Classifier: Programming Language :: Python :: 3.10
Classifier: Programming Language :: Python :: 3.11
Classifier: Programming Language :: Python :: 3.12
Classifier: Programming Language :: Python :: 3.13
Requires-Dist: langchain (>=0.3.26,<0.4.0)
Requires-Dist: langchain-core (>=0.3.67,<0.4.0)
Project-URL: Documentation, https://github.com/julienstitelet/langchain-pydantic-minifier#readme
Project-URL: Homepage, https://github.com/JulienStitelet/langchain-pydantic-minifier
Project-URL: Repository, https://github.com/julienstitelet/langchain-pydantic-minifier
